[
    {
    "fileName":"jielun1.png",
    "title":"Handsome JayChou",
    "desc":"JayChou is a very talented Singer."
    },
        {
    "fileName":"jielun2.png",
    "title":"Handsome JayChou",
    "desc":"JayChou is a very talented Singer."
    },
        {
    "fileName":"jielun3.png",
    "title":"Handsome JayChou",
    "desc":"JayChou is a very talented Singer."
    },
        {
    "fileName":"jielun4.png",
    "title":"Handsome JayChou",
    "desc":"JayChou is a very talented Singer."
    },
        {
    "fileName":"jielun5.png",
    "title":"Handsome JayChou",
    "desc":"JayChou is a very talented Singer."
    },
        {
    "fileName":"jielun6.png",
    "title":"Handsome JayChou",
    "desc":"JayChou is a very talented Singer."
    },
        {
    "fileName":"jielun7.png",
    "title":"Handsome JayChou",
    "desc":"JayChou is a very talented Singer."
    },
        {
    "fileName":"jielun8.png",
    "title":"Handsome JayChou",
    "desc":"JayChou is a very talented Singer."
    },
        {
    "fileName":"jielun9.png",
    "title":"Handsome JayChou",
    "desc":"JayChou is a very talented Singer."
    },
        {
    "fileName":"jielun10.png",
    "title":"Handsome JayChou",
    "desc":"JayChou is a very talented Singer."
    },
        {
    "fileName":"jielun11.png",
    "title":"Handsome JayChou",
    "desc":"JayChou is a very talented Singer."
    },
        {
    "fileName":"jielun12.png",
    "title":"Handsome JayChou",
    "desc":"JayChou is a very talented Singer."
    },
        {
    "fileName":"jielun13.png",
    "title":"Handsome JayChou",
    "desc":"JayChou is a very talented Singer."
    },
        {
    "fileName":"jielun14.png",
    "title":"Handsome JayChou",
    "desc":"JayChou is a very talented Singer."
    },
        {
    "fileName":"jielun15.png",
    "title":"Handsome JayChou",
    "desc":"JayChou is a very talented Singer."
    },
        {
    "fileName":"jielun16.png",
    "title":"Handsome JayChou",
    "desc":"JayChou is a very talented Singer.Yeah!"
    }
]